spark_app_library/__init__.py
spark_app_library/clickhouse_connection.py
spark_app_library/connection.py
spark_app_library/postgres_connection.py
spark_app_library/spark_app.py
spark_app_library/spark_app_config.py
spark_app_library/spark_app_library.py
spark_app_library-0.1.5.dist-info/METADATA
spark_app_library-0.1.5.dist-info/WHEEL
spark_app_library-0.1.5.dist-info/top_level.txt
spark_app_library-0.1.5.dist-info/RECORD
