Metadata-Version: 2.4
Name: spark-app-library
Version: 0.1.5
Summary: A library to simplify creating Spark apps.
Home-page: https://gitlab.snapp.ir/data-team/data-engineering/apache-spark/spark-app-library
Author: Navid Farhadi
Author-email: navid.farhadi@snapp.cab
Requires-Python: >=3.7
Dynamic: author
Dynamic: author-email
Dynamic: home-page
Dynamic: requires-python
Dynamic: summary
